odoo/addons/stock_secondary_unit/README.rst
odoo/addons/stock_secondary_unit/__init__.py
odoo/addons/stock_secondary_unit/__manifest__.py
odoo/addons/stock_secondary_unit/i18n/es.po
odoo/addons/stock_secondary_unit/i18n/stock_secondary_unit.pot
odoo/addons/stock_secondary_unit/migrations/11.0.1.0.2/post-migration.py
odoo/addons/stock_secondary_unit/models/__init__.py
odoo/addons/stock_secondary_unit/models/product.py
odoo/addons/stock_secondary_unit/models/stock_move.py
odoo/addons/stock_secondary_unit/readme/CONTRIBUTORS.rst
odoo/addons/stock_secondary_unit/readme/DESCRIPTION.rst
odoo/addons/stock_secondary_unit/readme/USAGE.rst
odoo/addons/stock_secondary_unit/report/report_deliveryslip.xml
odoo/addons/stock_secondary_unit/static/description/icon.png
odoo/addons/stock_secondary_unit/static/description/index.html
odoo/addons/stock_secondary_unit/tests/__init__.py
odoo/addons/stock_secondary_unit/tests/test_stock_secondary_unit.py
odoo/addons/stock_secondary_unit/views/product_views.xml
odoo/addons/stock_secondary_unit/views/stock_move_views.xml
odoo/addons/stock_secondary_unit/views/stock_picking_views.xml
odoo11_addon_stock_secondary_unit-11.0.1.0.4.dist-info/METADATA
odoo11_addon_stock_secondary_unit-11.0.1.0.4.dist-info/WHEEL
odoo11_addon_stock_secondary_unit-11.0.1.0.4.dist-info/top_level.txt
odoo11_addon_stock_secondary_unit-11.0.1.0.4.dist-info/RECORD
